<?xml version="1.0" encoding="windows-1251"?>

<!--
	Weapons
-->

<string_table>

<!--
	Varmageddon
-->

	<string id="st_knife_hunting">
		<text>Охотничий нож</text>
	</string>
	<string id="st_knife_hunting_descr">
		<text>Современный, высокопрочный охотничий нож с большим лезвием из нержавеющей стали. Идеально подходит для разделки мяса крупных животных с толстой шкурой. Он хорошо колет и режет открытую плоть, однако почти бесполезен против защищённых противников.\n \n
		%c[ui_gray_3]СВОЙСТВА:\n
		%c[d_cyan] • %c[ui_gray_2]холодное оружие\n
		%c[d_green] • %c[ui_gray_2]режет толстую шкуру?: %c[ui_green]ДА\n\n
		%c[d_red] • %c[ui_gray_2]Вармагеддон: %c[ui_green]60%%c[ui_gray_2] доп.урона мутантам
		</text>
	</string>
	
	<string id="st_axe">
		<text>Топор</text>
	</string>
	<string id="st_axe_descr">
		<text>Топор - это инструмент, который на протяжении тысячелетий использовался для работы с древесиной, в качестве оружия, а также как геральдический символ. Топор имеет множество форм, но обычно состоит из головки топора и топорища разной длинны. Хороший инструмент для выживания в Зоне.\n \n
		%c[ui_gray_3]СВОЙСТВА:\n
		%c[d_cyan] • %c[ui_gray_2]холодное оружие\n
		%c[d_green] • %c[ui_gray_2]больший охват по сравнению с ножами\n\n
		%c[d_red] • %c[ui_gray_2]Вармагеддон: %c[ui_green]60%%c[ui_gray_2] доп.урона мутантам
		</text>
	</string>
	
	<string id="st_axe2">
		<text>Пожарный топор</text>
	</string>
	<string id="st_axe2_descr">
		<text>Тяжёлый пожарный топор, часто применяется сталкерами для рубки дров или, как и любой топор, рубки врагов. Таким образом, в руках опытного сталкера он служит грозным оружием.\n \n
		%c[ui_gray_3]СВОЙСТВА:\n
		%c[d_cyan] • %c[ui_gray_2]холодное оружие\n
		%c[d_green] • %c[ui_gray_2]больший охват по сравнению с ножами\n\n
		%c[d_red] • %c[ui_gray_2]Вармагеддон: %c[ui_green]60%%c[ui_gray_2] доп.урона мутантам
		</text>
	</string>
	
<!--
	Ambush
-->
	
	<string id="st_knife_swat">
		<text>Нож спецназа</text>
	</string>
	<string id="st_knife_swat_descr">
		<text>Хорошо ухоженный клинок, идеально подходящий для оперативников, участвующих в спецоперациях. Хорошо пробивает броню и наносит тяжёлые раны. Идеальный боевой столовый прибор.\n \n
		%c[ui_gray_3]СВОЙСТВА:\n
		%c[d_cyan] • %c[ui_gray_2]холодное оружие\n
		%c[d_green] • %c[ui_gray_2]режет толстую шкуру?: %c[ui_green]ДА\n\n
		%c[d_red] • %c[ui_gray_2]Засада: %c[ui_green]20%%c[ui_gray_2] доп.урона и бронепробития из засады
		</text>
	</string>
	
	<string id="st_knife_combat">
		<text>Штык M9</text>
	</string>
	<string id="st_knife_combat_descr">
		<text>Большой многоцелевой нож с прорезиновой рукояткой, широко используемый солдатами США с 1986 года. Острый и хорошо держит заточку. Не очень эффективен против хорошей брони, но наносит тяжёлые ранения незащищённым целям. Это делает его идеальным выбором для добивания подранков или бесшумного добивания легкой пехоты.\n \n
		%c[ui_gray_3]СВОЙСТВА:\n
		%c[d_cyan] • %c[ui_gray_2]холодное оружие\n
		%c[d_green] • %c[ui_gray_2]режет толстую шкуру?: %c[ui_green]ДА\n\n
		%c[d_red] • %c[ui_gray_2]Засада: %c[ui_green]20%%c[ui_gray_2] доп.урона и бронепробития из засады
		</text>
	</string>
	
	<string id="st_kukri">
        	<text>Кукри</text>
    </string>
    <string id="st_kukri_descr">
        <text>Кукри - это разновидность мачете, традиционная для Непала. Он может работать как оружие ближнего боя, так и инструмент для рубки мелких веток и кустов, чему способствует характерно загнутое лезвие.\n \n
		%c[0,255,255,255]СВОЙСТВА:\n
		%c[d_cyan] • %c[ui_gray_2]холодное оружие\n
		%c[d_green] • %c[ui_gray_2]режет толстую шкуру?: %c[ui_green]ДА\n\n
		%c[d_red] • %c[ui_gray_2]Засада: %c[ui_green]20%%c[ui_gray_2] доп.урона и бронепробития из засады
		</text>
	</string>
	
	<string id="st_tomahawk">
		<text>Томагавк Gerber Downrange </text>
	</string>
	<string id="st_tomahawk_descr">
		<text>Универсальный тактический томагавк, подходит для всех боевых ситуаций.\n \n
		%c[0,255,255,255]СВОЙСТВА:\n
		%c[d_cyan] • %c[ui_gray_2]холодное оружие\n
		%c[d_green] • %c[ui_gray_2]режет толстую шкуру?: %c[ui_green]ДА\n\n
		%c[d_red] • %c[ui_gray_2]Засада: %c[ui_green]20%%c[ui_gray_2] доп.урона и бронепробития из засады
		</text>
	</string>
	
<!--
	Headhunter
-->
	<string id="st_axe3">
		<text>Охотничий топор</text>
	</string>
	<string id="st_axe3_descr">
		<text>Топор - это инструмент, который на протяжении тысячелетий использовался для работы с древесиной, в качестве оружия, а также как геральдический символ. Топор имеет множество форм, но обычно состоит из головки топора и топорища разной длинны. Хороший инструмент для выживания в Зоне.\n \n
		%c[ui_gray_3]СВОЙСТВА:\n
		%c[d_cyan] • %c[ui_gray_2]холодное оружие\n
		%c[d_green] • %c[ui_gray_2]больший охват по сравнению с ножами\n\n
		%c[d_red] • %c[ui_gray_2]Охотник за головами: Полностью %c[ui_green]игнорирует броню%c[ui_gray_2] при ударе по голове
		</text>
	</string>
	
</string_table>